agentmesh/__init__.py
agentmesh/api/__init__.py
agentmesh/api/main.py
agentmesh/api/middleware.py
agentmesh/api/routers/__init__.py
agentmesh/api/routers/agents.py
agentmesh/api/routers/auth.py
agentmesh/api/routers/context.py
agentmesh/api/routers/handoffs.py
agentmesh/api/routers/health.py
agentmesh/api/routers/messaging.py
agentmesh/api/routers/websocket.py
agentmesh/api/routers/workflows.py
agentmesh/cli/__main__.py
agentmesh/cli/commands/__init__.py
agentmesh/cli/commands/agent.py
agentmesh/cli/commands/auth.py
agentmesh/cli/commands/server.py
agentmesh/cli/commands/workflow.py
agentmesh/core/__init__.py
agentmesh/core/agent_manager.py
agentmesh/core/config.py
agentmesh/core/context_manager.py
agentmesh/core/handoff_manager.py
agentmesh/db/__init__.py
agentmesh/db/database.py
agentmesh/db/models.py
agentmesh/messaging/__init__.py
agentmesh/messaging/message_bus.py
agentmesh/models/__init__.py
agentmesh/models/agent.py
agentmesh/orchestration/__init__.py
agentmesh/orchestration/base.py
agentmesh/orchestration/graph.py
agentmesh/orchestration/round_robin.py
agentmesh/orchestration/sequential.py
agentmesh/orchestration/swarm.py
agentmesh/security/__init__.py
agentmesh/security/auth.py
agentmesh/security/permissions.py
agentmesh/security/rate_limiting.py
agentmesh/workflows/__init__.py
agentmesh/workflows/config.py
agentmesh/workflows/manager.py
agentmesh_orchestrator-0.1.5.dist-info/METADATA
agentmesh_orchestrator-0.1.5.dist-info/WHEEL
agentmesh_orchestrator-0.1.5.dist-info/entry_points.txt
agentmesh_orchestrator-0.1.5.dist-info/RECORD
