Metadata-Version: 2.3
Name: agentmesh-orchestrator
Version: 0.1.5
Summary: AgentMesh - Multi-Agent Orchestration Platform
Keywords: multi-agent,orchestration,autogen,ai,workflow
Author: Development Team
Author-email: dev@agentmesh.ai
Requires-Python: >=3.11,<3.14
Classifier: Development Status :: 3 - Alpha
Classifier: Intended Audience :: Developers
Classifier: License :: OSI Approved :: MIT License
Classifier: Programming Language :: Python :: 3
Classifier: Programming Language :: Python :: 3.11
Classifier: Programming Language :: Python :: 3.12
Classifier: Programming Language :: Python :: 3.13
Classifier: Topic :: Scientific/Engineering :: Artificial Intelligence
Classifier: Topic :: Software Development :: Libraries :: Python Modules
Requires-Dist: aiosqlite (>=0.20.0,<0.21.0)
Requires-Dist: alembic (>=1.13.0,<2.0.0)
Requires-Dist: autogen-agentchat (>=0.2.0,<0.3.0)
Requires-Dist: autogen-core (>=0.4.0,<0.5.0)
Requires-Dist: autogen-ext (>=0.4.0,<0.5.0)
Requires-Dist: boto3 (>=1.34.149,<2.0.0)
Requires-Dist: cryptography (>=41.0.0,<50.0.0)
Requires-Dist: deprecated (>=1.2.14,<2.0.0)
Requires-Dist: fastapi (>=0.108.0,<0.109.0)
Requires-Dist: httpx (>=0.26.0,<1.0.0)
Requires-Dist: opentelemetry-api (>=1.21.0,<2.0.0)
Requires-Dist: opentelemetry-exporter-jaeger (>=1.21.0,<2.0.0)
Requires-Dist: opentelemetry-sdk (>=1.21.0,<2.0.0)
Requires-Dist: passlib[bcrypt] (>=1.7.4,<2.0.0)
Requires-Dist: prometheus-client (>=0.19.0,<0.20.0)
Requires-Dist: pydantic (>=2.5.0,<3.0.0)
Requires-Dist: pydantic-settings (>=2.1.0,<3.0.0)
Requires-Dist: python-jose[cryptography] (>=3.3.0,<4.0.0)
Requires-Dist: python-multipart (>=0.0.20,<0.0.21)
Requires-Dist: pyyaml (>=6.0,<7.0)
Requires-Dist: redis[hiredis] (>=6.4.0,<7.0.0)
Requires-Dist: rich (>=13.7.0,<14.0.0)
Requires-Dist: sqlalchemy (>=2.0.0,<3.0.0)
Requires-Dist: typer (>=0.9.0,<0.10.0)
Requires-Dist: uvicorn[standard] (>=0.25.0,<0.26.0)
Requires-Dist: websockets (>=12.0,<13.0)
Project-URL: Documentation, https://github.com/akhilthomas236/agentmesh/blob/main/README.md
Project-URL: Homepage, https://github.com/akhilthomas236/agentmesh
Project-URL: Repository, https://github.com/akhilthomas236/agentmesh
